unicode_linebreak-0.0.2.dist-info/METADATA
unicode_linebreak-0.0.2.dist-info/WHEEL
unicode_linebreak/__init__.py
unicode_linebreak/unicode_linebreak.cpython-37m-darwin.so
unicode_linebreak-0.0.2.dist-info/RECORD
